pdairp/__init__.py
pdairp/o3yoccurinfo.py
pdairp/pollutiondata.py
pdairp/pollutionstats.py
pdairp/stationinfo.py
pypubdata-0.1.4.1.dist-info/METADATA
pypubdata-0.1.4.1.dist-info/RECORD
pypubdata-0.1.4.1.dist-info/WHEEL
pypubdata-0.1.4.1.dist-info/top_level.txt
