Metadata-Version: 2.1
Name: pypubdata
Version: 0.1.4.1
Summary: It is simple module package for ROK Public Data OpenAPI.
Home-page: https://github.com/gomgomdev/pypubdata
Author: Gomgom
Author-email: dev@gomgom.io
License: lGPLv3
Download-URL: https://github.com/gomgomdev/pypubdata/archive/master.zip
Platform: UNKNOWN
Classifier: Programming Language :: Python
Classifier: Programming Language :: Python :: 3.5
